jinjasql/__init__.py
jinjasql/core.py
jinjasql2-0.1.12.dist-info/LICENSE
jinjasql2-0.1.12.dist-info/METADATA
jinjasql2-0.1.12.dist-info/WHEEL
jinjasql2-0.1.12.dist-info/top_level.txt
jinjasql2-0.1.12.dist-info/RECORD
