Metadata-Version: 2.1
Name: jinjasql2
Version: 0.1.12
Summary: Generate SQL Queries and Corresponding Bind Parameters using a Jinja2 Template
Home-page: https://github.com/pythonutilities/jinjasql
Download-URL: http://cloud.github.com/downloads/pythonutilities/jinjasql/jinjasql-0.1.12.tar.gz
Author: Sridhar, Thomas Ashish Cherian, Sripathi Krishnan
Author-email: crsridhar23@gmail.com
Maintainer: Sridhar, Thomas Ashish Cherian
Maintainer-email: crsridhar23@gmail.com
License: MIT
Keywords: Jinja2,SQL,Python,Template
Classifier: Development Status :: 4 - Beta
Classifier: Environment :: Console
Classifier: Intended Audience :: Developers
Classifier: License :: OSI Approved :: MIT License
Classifier: Operating System :: OS Independent
Classifier: Programming Language :: Python
Classifier: Programming Language :: Python :: 2.7
Classifier: Programming Language :: Python :: 3
License-File: LICENSE
Requires-Dist: Jinja2>=2.11.3
